README.md
setup.py
distributions_jks/__init__.py
distributions_jks.egg-info/PKG-INFO
distributions_jks.egg-info/SOURCES.txt
distributions_jks.egg-info/dependency_links.txt
distributions_jks.egg-info/not-zip-safe
distributions_jks.egg-info/top_level.txt